agent2agent/__init__.py
agent2agent/types.py
agent2agent/client/__init__.py
agent2agent/client/card_resolver.py
agent2agent/client/client.py
agent2agent/server/__init__.py
agent2agent/server/server.py
agent2agent/server/task_manager.py
agent2agent/server/utils.py
agent2agent/utils/__init__.py
agent2agent/utils/in_memory_cache.py
agent2agent/utils/push_notification_auth.py
ai_agent2agent-0.1.1.dist-info/METADATA
ai_agent2agent-0.1.1.dist-info/WHEEL
ai_agent2agent-0.1.1.dist-info/top_level.txt
ai_agent2agent-0.1.1.dist-info/RECORD
