Metadata-Version: 2.4
Name: ai_agent2agent
Version: 0.1.1
Summary: A Python library for Agent-to-Agent communication
Author: Eligapris
Author-email: 
Project-URL: Homepage, https://github.com/your-username/ai_agent2agent
Project-URL: Bug Tracker, https://github.com/your-username/ai_agent2agent/issues
Classifier: Development Status :: 3 - Alpha
Classifier: Intended Audience :: Developers
Classifier: Programming Language :: Python :: 3
Classifier: Programming Language :: Python :: 3.8
Classifier: Programming Language :: Python :: 3.9
Classifier: Programming Language :: Python :: 3.10
Requires-Python: >=3.8
Requires-Dist: pydantic>=2.0.0
Requires-Dist: typing-extensions>=4.0.0
Requires-Dist: starlette>=0.28.0
Requires-Dist: sse-starlette>=1.0.0
Requires-Dist: uvicorn>=0.22.0
Requires-Dist: asyncio>=3.4.3
Requires-Dist: jwcrypto>=1.5.0
Dynamic: requires-python
